{
    "business": [
      {
        "name": "First Watch",
        "phone": "(205) 979-6827",
        "address": "700 Montgomery Highway, Suite 188<br>Vestavia Hills, AL 35216",
        "site": "https://www.firstwatch.com",
        "logo": "https://d3uelt8k02tx43.cloudfront.net/wp-content/themes/theme_firstwatch/assets/production/images/first-watch-logo@2x.png"
      },
      {
        "name": "The Backyard Market",
        "phone": "(205) 637-5731",
        "address": "633 Montgomery Highway<br>Vestavia Hills, AL 35216",
        "site": "https://www.facebook.com/backyardmarketvestavia",
        "logo": "https://scontent-atl3-1.xx.fbcdn.net/v/t1.6435-9/126095338_107783031161108_8791687042921121739_n.png?_nc_cat=102&ccb=1-3&_nc_sid=973b4a&_nc_ohc=88dM0GB10QQAX84q0rg&_nc_ht=scontent-atl3-1.xx&oh=04b3d5e1f7eac36270baac4bd82b2107&oe=60948C1D"
      },
      {
        "name": "Satterfield's",
        "phone": "(205) 969-9690",
        "address": "3161 Cahaba Heights Road, Suite 113<br>Vestavia Hills, Alabama 35243",
        "site": "https://www.satterfieldsrestaurant.com",
        "logo": "https://www.satterfieldsrestaurant.com/uploads/b/a99f66473586cecb9b9cdc9d07059d94d94583af41c020376736ab4b921aad17/Satterfields-Logo_1593279963.png?width=400"
      },
      {
        "name": "Alan & Co. Jewelers",
        "phone": "(205) 769-6930",
        "address": "619 Montgomery Highway<br>Vestavia Hills, AL 35216",
        "site": "https://alanandco.jewelershowcase.com",
        "logo": "https://meteor.stullercloud.com/das/22255674?$standard$&$sharpenpng$"
      },
      {
        "name": "Andy's Creekside Nursery",
        "phone": "(205) 824-0233",
        "address": "3351 Morgan Drive<br>Vestavia Hills, AL 35216",
        "site": "https://andysgardencenter.com",
        "logo": "https://andysgardencenter.com/wp-content/uploads/2015/09/logo.png"
      },
      {
        "name": "The Blue Willow",
        "phone": "(205) 968-0909",
        "address": "3930 Crosshaven Drive<br>Vestavia Hills, AL 35243",
        "site": "https://www.thebluewillow.com",
        "logo": "https://www.thebluewillow.com/images/logo_link.png"
      },
      {
        "name": "Vestavia Bowl",
        "phone": "(205) 979-4420",
        "address": "1429 Montgomery Highway<br>Vestavia Hills, AL 35216",
        "site": "https://www.vestaviabowl.com",
        "logo": "https://growthzonesitesprod.azureedge.net/wp-content/uploads/sites/1501/2021/01/Vestavia-Bowl-258x300.png"
      },
      {
        "name": "Mason Music",
        "phone": "(205) 908-7059",
        "address": "3187 Cahaba Heights Road<br>Vestavia Hills, AL 35243",
        "site": "https://masonmusicstudios.com",
        "logo": "https://growthzonesitesprod.azureedge.net/wp-content/uploads/sites/1501/2021/01/Mason-Music-horizontal-300x99.png"
      },
      {
        "name": "Cahaba Fitness",
        "phone": "(205) 968-5100",
        "address": "3161 Cahaba Heights Road, Suite 217<br>Vestavia Hills, AL 35243",
        "site": "https://www.cahabafitness.com",
        "logo": "https://static.wixstatic.com/media/e7a27b_0b70c2d3a0be4983a1c2dae8be548025~mv2.png/v1/fill/w_312,h_65,al_c,q_85,usm_0.66_1.00_0.01/e7a27b_0b70c2d3a0be4983a1c2dae8be548025~mv2.webp"
      }
    ]
  }